chr_struct_logging/__init__.py
chr_struct_logging/chr_struct_logging.py
chr_struct_logging-0.1.1.dist-info/AUTHORS.rst
chr_struct_logging-0.1.1.dist-info/LICENSE
chr_struct_logging-0.1.1.dist-info/METADATA
chr_struct_logging-0.1.1.dist-info/WHEEL
chr_struct_logging-0.1.1.dist-info/top_level.txt
chr_struct_logging-0.1.1.dist-info/RECORD
